lbl_python-0.1.0.dist-info/METADATA
lbl_python-0.1.0.dist-info/WHEEL
lbl/_query.py
lbl/__init__.py
lbl/_lbl_rust.cpython-311-darwin.so
lbl_python-0.1.0.dist-info/RECORD
