Metadata-Version: 2.1
Name: lbl_python
Version: 0.1.0
Classifier: Programming Language :: Rust
Classifier: Programming Language :: Python :: Implementation :: CPython
Classifier: Programming Language :: Python :: Implementation :: PyPy
Summary: lbl
Home-Page: https://github.com/paradigmxyz/lbl
License: MIT OR Apache-2.0
Requires-Python: >=3.7
Project-URL: Source Code, https://github.com/paradigmxyz/lbl
